{
    "5158": {
        "id": 5158,
        "name": "necrolyte_death_pulse",
        "name_loc": "Death Pulse",
        "desc_loc": "Necrophos releases a wave of death around him, dealing damage to enemy units and healing allied units.",
        "lore_loc": "Poor souls who succumb to Rotund'jere's plagues are recycled for future use.",
        "notes_loc": [
            "Death Pulse can't be disjointed.",
            "Can heal Spell Immune units."
        ],
        "shard_loc": "",
        "scepter_loc": "",
        "type": 0,
        "behavior": "4",
        "target_team": 0,
        "target_type": 0,
        "flags": 0,
        "damage": 2,
        "immunity": 4,
        "dispellable": 0,
        "max_level": 4,
        "cast_ranges": [
            0
        ],
        "cast_points": [
            0,
            0,
            0,
            0
        ],
        "channel_times": [
            0,
            0,
            0,
            0
        ],
        "cooldowns": [
            8,
            7,
            6,
            5
        ],
        "durations": [
            0,
            0,
            0,
            0
        ],
        "damages": [
            100,
            150,
            200,
            250
        ],
        "mana_costs": [
            100,
            130,
            160,
            190
        ],
        "gold_costs": [],
        "special_values": [
            {
                "name": "area_of_effect",
                "values_float": [],
                "values_int": [
                    500
                ],
                "is_percentage": false,
                "heading_loc": "RADIUS:"
            },
            {
                "name": "heal",
                "values_float": [],
                "values_int": [
                    60,
                    80,
                    100,
                    120
                ],
                "is_percentage": false,
                "heading_loc": "HEAL:"
            },
            {
                "name": "projectile_speed",
                "values_float": [],
                "values_int": [
                    400
                ],
                "is_percentage": false,
                "heading_loc": ""
            },
            {
                "name": "#AbilityDamage",
                "values_float": [],
                "values_int": [
                    100,
                    150,
                    200,
                    250
                ],
                "is_percentage": false,
                "heading_loc": ""
            }
        ],
        "is_item": false,
        "ability_has_scepter": false,
        "ability_has_shard": false,
        "ability_is_granted_by_scepter": false,
        "ability_is_granted_by_shard": false,
        "item_cost": 0,
        "item_initial_charges": 0,
        "item_neutral_tier": 4294967295,
        "item_stock_max": 0,
        "item_stock_time": 0,
        "item_quality": 0
    },
    "5160": {
        "id": 5160,
        "name": "necrolyte_sadist",
        "name_loc": "Ghost Shroud",
        "desc_loc": "Necrophos slips into the realm that separates the living from the dead. Unable to attack or be attacked, he emits an aura that slows enemies around him. He takes additional magic damage in this form, but his restorative powers are amplified.",
        "lore_loc": "Rotund'jere uses the souls of his victims as bridge from life to afterlife.",
        "notes_loc": [],
        "shard_loc": "",
        "scepter_loc": "Reduces Ghost Shroud cooldown.",
        "type": 0,
        "behavior": "2052",
        "target_team": 0,
        "target_type": 0,
        "flags": 0,
        "damage": 0,
        "immunity": 4,
        "dispellable": 2,
        "max_level": 4,
        "cast_ranges": [
            0
        ],
        "cast_points": [
            0
        ],
        "channel_times": [
            0,
            0,
            0,
            0
        ],
        "cooldowns": [
            28,
            24,
            20,
            16
        ],
        "durations": [
            0,
            0,
            0,
            0
        ],
        "damages": [
            0,
            0,
            0,
            0
        ],
        "mana_costs": [
            50
        ],
        "gold_costs": [],
        "special_values": [
            {
                "name": "duration",
                "values_float": [
                    3,
                    3.5,
                    4,
                    4.5
                ],
                "values_int": [],
                "is_percentage": false,
                "heading_loc": "DURATION:"
            },
            {
                "name": "heal_bonus",
                "values_float": [],
                "values_int": [
                    75
                ],
                "is_percentage": true,
                "heading_loc": "RESTORATION AMPLIFICATION:"
            },
            {
                "name": "movement_speed",
                "values_float": [],
                "values_int": [
                    12,
                    16,
                    20,
                    24
                ],
                "is_percentage": true,
                "heading_loc": "MOVEMENT SLOW:"
            },
            {
                "name": "slow_aoe",
                "values_float": [],
                "values_int": [
                    750
                ],
                "is_percentage": false,
                "heading_loc": "SLOW RADIUS:"
            },
            {
                "name": "bonus_damage",
                "values_float": [],
                "values_int": [
                    -40
                ],
                "is_percentage": true,
                "heading_loc": "INCREASED MAGIC DAMAGE:"
            },
            {
                "name": "cooldown_scepter",
                "values_float": [],
                "values_int": [
                    10
                ],
                "is_percentage": false,
                "heading_loc": "SCEPTER COOLDOWN:"
            }
        ],
        "is_item": false,
        "ability_has_scepter": true,
        "ability_has_shard": false,
        "ability_is_granted_by_scepter": false,
        "ability_is_granted_by_shard": false,
        "item_cost": 0,
        "item_initial_charges": 0,
        "item_neutral_tier": 4294967295,
        "item_stock_max": 0,
        "item_stock_time": 0,
        "item_quality": 0
    },
    "5159": {
        "id": 5159,
        "name": "necrolyte_heartstopper_aura",
        "name_loc": "Heartstopper Aura",
        "desc_loc": "Necrophos stills the hearts of his opponents, causing nearby enemy units to lose a percentage of their max health over time. Passively provides regen for %regen_duration% seconds for each unit Necrophos kills.",
        "lore_loc": "Those who come within a short distance of Necrophos can feel pestilence and plague in the air.",
        "notes_loc": [
            "Damage won't disable items like Blink Dagger.",
            "Does not affect ancient creeps."
        ],
        "shard_loc": "",
        "scepter_loc": "Increases Heartstopper Aura damage while Ghost Shroud is active.",
        "type": 0,
        "behavior": "65538",
        "target_team": 2,
        "target_type": 0,
        "flags": 0,
        "damage": 2,
        "immunity": 4,
        "dispellable": 0,
        "max_level": 4,
        "cast_ranges": [
            0
        ],
        "cast_points": [
            0,
            0,
            0,
            0
        ],
        "channel_times": [
            0,
            0,
            0,
            0
        ],
        "cooldowns": [
            0,
            0,
            0,
            0
        ],
        "durations": [
            0,
            0,
            0,
            0
        ],
        "damages": [
            0,
            0,
            0,
            0
        ],
        "mana_costs": [
            0,
            0,
            0,
            0
        ],
        "gold_costs": [],
        "special_values": [
            {
                "name": "aura_radius",
                "values_float": [],
                "values_int": [
                    800
                ],
                "is_percentage": false,
                "heading_loc": "RADIUS:"
            },
            {
                "name": "aura_damage",
                "values_float": [
                    0.60000002384186,
                    1.2000000476837,
                    1.7999999523163,
                    2.4000000953674
                ],
                "values_int": [],
                "is_percentage": true,
                "heading_loc": "HEALTH DECAY:"
            },
            {
                "name": "health_regen",
                "values_float": [
                    4,
                    5,
                    6,
                    7
                ],
                "values_int": [],
                "is_percentage": false,
                "heading_loc": "HEALTH REGEN PER KILL:"
            },
            {
                "name": "mana_regen",
                "values_float": [
                    4,
                    5,
                    6,
                    7
                ],
                "values_int": [],
                "is_percentage": false,
                "heading_loc": "MANA REGEN PER KILL:"
            },
            {
                "name": "hero_multiplier",
                "values_float": [],
                "values_int": [
                    6
                ],
                "is_percentage": false,
                "heading_loc": "HERO KILL REGEN MULTIPLIER:"
            },
            {
                "name": "regen_duration",
                "values_float": [
                    8
                ],
                "values_int": [],
                "is_percentage": false,
                "heading_loc": "REGEN DURATION:"
            },
            {
                "name": "scepter_multiplier",
                "values_float": [
                    2
                ],
                "values_int": [],
                "is_percentage": false,
                "heading_loc": "SCEPTER DAMAGE MULTIPLIER:"
            }
        ],
        "is_item": false,
        "ability_has_scepter": true,
        "ability_has_shard": false,
        "ability_is_granted_by_scepter": false,
        "ability_is_granted_by_shard": false,
        "item_cost": 0,
        "item_initial_charges": 0,
        "item_neutral_tier": 4294967295,
        "item_stock_max": 0,
        "item_stock_time": 0,
        "item_quality": 0
    },
    "661": {
        "id": 661,
        "name": "necrolyte_death_seeker",
        "name_loc": "Death Seeker",
        "desc_loc": "Spawns a fast moving large Death Pulse towards the target enemy or ally, causing the target to become ethereal for 2.5 seconds. Reduces enemy magic resistance by 25%. Spreads towards nearby enemies and allies after impact.",
        "lore_loc": "",
        "notes_loc": [],
        "shard_loc": "",
        "scepter_loc": "",
        "type": 0,
        "behavior": "8589934601",
        "target_team": 3,
        "target_type": 19,
        "flags": 0,
        "damage": 2,
        "immunity": 4,
        "dispellable": 2,
        "max_level": 1,
        "cast_ranges": [
            900
        ],
        "cast_points": [
            0.20000000298023
        ],
        "channel_times": [
            0,
            0,
            0,
            0
        ],
        "cooldowns": [
            14
        ],
        "durations": [
            0,
            0,
            0,
            0
        ],
        "damages": [
            0,
            0,
            0,
            0
        ],
        "mana_costs": [
            100
        ],
        "gold_costs": [],
        "special_values": [
            {
                "name": "projectile_multiplier",
                "values_float": [
                    125
                ],
                "values_int": [],
                "is_percentage": false,
                "heading_loc": ""
            },
            {
                "name": "AbilityCastRange",
                "values_float": [],
                "values_int": [
                    900
                ],
                "is_percentage": false,
                "heading_loc": ""
            },
            {
                "name": "AbilityCastPoint",
                "values_float": [
                    0.20000000298023
                ],
                "values_int": [],
                "is_percentage": false,
                "heading_loc": ""
            }
        ],
        "is_item": false,
        "ability_has_scepter": false,
        "ability_has_shard": false,
        "ability_is_granted_by_scepter": false,
        "ability_is_granted_by_shard": true,
        "item_cost": 0,
        "item_initial_charges": 0,
        "item_neutral_tier": 4294967295,
        "item_stock_max": 0,
        "item_stock_time": 0,
        "item_quality": 0
    },
    "5161": {
        "id": 5161,
        "name": "necrolyte_reapers_scythe",
        "name_loc": "Reaper's Scythe",
        "desc_loc": "Stuns the target enemy hero, then deals damage based on how much life it is missing. Heroes killed by Reaper's Scythe will have %respawn_constant% seconds added to their respawn timer. Any kill under this effect is credited to Necrophos.",
        "lore_loc": "The amount of death and suffering in the air increases the power of Necrophos's plague magic.",
        "notes_loc": [
            "Damage is dealt at the end of the stun."
        ],
        "shard_loc": "",
        "scepter_loc": "",
        "type": 1,
        "behavior": "8",
        "target_team": 2,
        "target_type": 1,
        "flags": 0,
        "damage": 2,
        "immunity": 4,
        "dispellable": 3,
        "max_level": 3,
        "cast_ranges": [
            600
        ],
        "cast_points": [
            0.44999998807907
        ],
        "channel_times": [
            0,
            0,
            0,
            0
        ],
        "cooldowns": [
            120
        ],
        "durations": [
            0,
            0,
            0,
            0
        ],
        "damages": [
            0,
            0,
            0,
            0
        ],
        "mana_costs": [
            200,
            350,
            500
        ],
        "gold_costs": [],
        "special_values": [
            {
                "name": "damage_per_health",
                "values_float": [
                    0.69999998807907,
                    0.80000001192093,
                    0.89999997615814
                ],
                "values_int": [],
                "is_percentage": false,
                "heading_loc": "DAMAGE PER MISSING HP:"
            },
            {
                "name": "stun_duration",
                "values_float": [
                    1.5
                ],
                "values_int": [],
                "is_percentage": false,
                "heading_loc": "STUN DURATION:"
            },
            {
                "name": "respawn_constant",
                "values_float": [],
                "values_int": [
                    15,
                    25,
                    35
                ],
                "is_percentage": false,
                "heading_loc": "ADDED RESPAWN TIME:"
            },
            {
                "name": "AbilityCastRange",
                "values_float": [],
                "values_int": [
                    600
                ],
                "is_percentage": false,
                "heading_loc": ""
            },
            {
                "name": "AbilityCastPoint",
                "values_float": [
                    0.44999998807907
                ],
                "values_int": [],
                "is_percentage": false,
                "heading_loc": ""
            }
        ],
        "is_item": false,
        "ability_has_scepter": false,
        "ability_has_shard": false,
        "ability_is_granted_by_scepter": false,
        "ability_is_granted_by_shard": false,
        "item_cost": 0,
        "item_initial_charges": 0,
        "item_neutral_tier": 4294967295,
        "item_stock_max": 0,
        "item_stock_time": 0,
        "item_quality": 0
    },
    "6009": {
        "id": 6009,
        "name": "special_bonus_attack_damage_25",
        "name_loc": "+{s:value} Damage",
        "desc_loc": "",
        "lore_loc": "",
        "notes_loc": [],
        "shard_loc": "",
        "scepter_loc": "",
        "type": 2,
        "behavior": "2",
        "target_team": 0,
        "target_type": 0,
        "flags": 0,
        "damage": 0,
        "immunity": 0,
        "dispellable": 0,
        "max_level": 4,
        "cast_ranges": [
            0
        ],
        "cast_points": [
            0,
            0,
            0,
            0
        ],
        "channel_times": [
            0,
            0,
            0,
            0
        ],
        "cooldowns": [
            0,
            0,
            0,
            0
        ],
        "durations": [
            0,
            0,
            0,
            0
        ],
        "damages": [
            0,
            0,
            0,
            0
        ],
        "mana_costs": [
            0,
            0,
            0,
            0
        ],
        "gold_costs": [],
        "special_values": [
            {
                "name": "value",
                "values_float": [],
                "values_int": [
                    25
                ],
                "is_percentage": false,
                "heading_loc": ""
            }
        ],
        "is_item": false,
        "ability_has_scepter": false,
        "ability_has_shard": false,
        "ability_is_granted_by_scepter": false,
        "ability_is_granted_by_shard": false,
        "item_cost": 0,
        "item_initial_charges": 0,
        "item_neutral_tier": 4294967295,
        "item_stock_max": 0,
        "item_stock_time": 0,
        "item_quality": 0
    },
    "5982": {
        "id": 5982,
        "name": "special_bonus_strength_8",
        "name_loc": "+{s:value} Strength",
        "desc_loc": "",
        "lore_loc": "",
        "notes_loc": [],
        "shard_loc": "",
        "scepter_loc": "",
        "type": 2,
        "behavior": "2",
        "target_team": 0,
        "target_type": 0,
        "flags": 0,
        "damage": 0,
        "immunity": 0,
        "dispellable": 0,
        "max_level": 4,
        "cast_ranges": [
            0
        ],
        "cast_points": [
            0,
            0,
            0,
            0
        ],
        "channel_times": [
            0,
            0,
            0,
            0
        ],
        "cooldowns": [
            0,
            0,
            0,
            0
        ],
        "durations": [
            0,
            0,
            0,
            0
        ],
        "damages": [
            0,
            0,
            0,
            0
        ],
        "mana_costs": [
            0,
            0,
            0,
            0
        ],
        "gold_costs": [],
        "special_values": [
            {
                "name": "value",
                "values_float": [],
                "values_int": [
                    8
                ],
                "is_percentage": false,
                "heading_loc": ""
            }
        ],
        "is_item": false,
        "ability_has_scepter": false,
        "ability_has_shard": false,
        "ability_is_granted_by_scepter": false,
        "ability_is_granted_by_shard": false,
        "item_cost": 0,
        "item_initial_charges": 0,
        "item_neutral_tier": 4294967295,
        "item_stock_max": 0,
        "item_stock_time": 0,
        "item_quality": 0
    },
    "7110": {
        "id": 7110,
        "name": "special_bonus_unique_necrophos_3",
        "name_loc": "+{s:value}% Ghost Shroud Slow",
        "desc_loc": "",
        "lore_loc": "",
        "notes_loc": [],
        "shard_loc": "",
        "scepter_loc": "",
        "type": 2,
        "behavior": "2",
        "target_team": 0,
        "target_type": 0,
        "flags": 0,
        "damage": 0,
        "immunity": 0,
        "dispellable": 0,
        "max_level": 4,
        "cast_ranges": [
            0
        ],
        "cast_points": [
            0,
            0,
            0,
            0
        ],
        "channel_times": [
            0,
            0,
            0,
            0
        ],
        "cooldowns": [
            0,
            0,
            0,
            0
        ],
        "durations": [
            0,
            0,
            0,
            0
        ],
        "damages": [
            0,
            0,
            0,
            0
        ],
        "mana_costs": [
            0,
            0,
            0,
            0
        ],
        "gold_costs": [],
        "special_values": [
            {
                "name": "value",
                "values_float": [],
                "values_int": [
                    24
                ],
                "is_percentage": false,
                "heading_loc": ""
            }
        ],
        "is_item": false,
        "ability_has_scepter": false,
        "ability_has_shard": false,
        "ability_is_granted_by_scepter": false,
        "ability_is_granted_by_shard": false,
        "item_cost": 0,
        "item_initial_charges": 0,
        "item_neutral_tier": 4294967295,
        "item_stock_max": 0,
        "item_stock_time": 0,
        "item_quality": 0
    },
    "7111": {
        "id": 7111,
        "name": "special_bonus_unique_necrophos_4",
        "name_loc": "+{s:value} Death Pulse Heal",
        "desc_loc": "",
        "lore_loc": "",
        "notes_loc": [],
        "shard_loc": "",
        "scepter_loc": "",
        "type": 2,
        "behavior": "2",
        "target_team": 0,
        "target_type": 0,
        "flags": 0,
        "damage": 0,
        "immunity": 0,
        "dispellable": 0,
        "max_level": 4,
        "cast_ranges": [
            0
        ],
        "cast_points": [
            0,
            0,
            0,
            0
        ],
        "channel_times": [
            0,
            0,
            0,
            0
        ],
        "cooldowns": [
            0,
            0,
            0,
            0
        ],
        "durations": [
            0,
            0,
            0,
            0
        ],
        "damages": [
            0,
            0,
            0,
            0
        ],
        "mana_costs": [
            0,
            0,
            0,
            0
        ],
        "gold_costs": [],
        "special_values": [
            {
                "name": "value",
                "values_float": [],
                "values_int": [
                    32
                ],
                "is_percentage": false,
                "heading_loc": ""
            }
        ],
        "is_item": false,
        "ability_has_scepter": false,
        "ability_has_shard": false,
        "ability_is_granted_by_scepter": false,
        "ability_is_granted_by_shard": false,
        "item_cost": 0,
        "item_initial_charges": 0,
        "item_neutral_tier": 4294967295,
        "item_stock_max": 0,
        "item_stock_time": 0,
        "item_quality": 0
    },
    "6138": {
        "id": 6138,
        "name": "special_bonus_magic_resistance_15",
        "name_loc": "+{s:value}% Magic Resistance",
        "desc_loc": "",
        "lore_loc": "",
        "notes_loc": [],
        "shard_loc": "",
        "scepter_loc": "",
        "type": 2,
        "behavior": "2",
        "target_team": 0,
        "target_type": 0,
        "flags": 0,
        "damage": 0,
        "immunity": 0,
        "dispellable": 0,
        "max_level": 4,
        "cast_ranges": [
            0
        ],
        "cast_points": [
            0,
            0,
            0,
            0
        ],
        "channel_times": [
            0,
            0,
            0,
            0
        ],
        "cooldowns": [
            0,
            0,
            0,
            0
        ],
        "durations": [
            0,
            0,
            0,
            0
        ],
        "damages": [
            0,
            0,
            0,
            0
        ],
        "mana_costs": [
            0,
            0,
            0,
            0
        ],
        "gold_costs": [],
        "special_values": [
            {
                "name": "value",
                "values_float": [],
                "values_int": [
                    15
                ],
                "is_percentage": false,
                "heading_loc": ""
            }
        ],
        "is_item": false,
        "ability_has_scepter": false,
        "ability_has_shard": false,
        "ability_is_granted_by_scepter": false,
        "ability_is_granted_by_shard": false,
        "item_cost": 0,
        "item_initial_charges": 0,
        "item_neutral_tier": 4294967295,
        "item_stock_max": 0,
        "item_stock_time": 0,
        "item_quality": 0
    },
    "350": {
        "id": 350,
        "name": "special_bonus_unique_necrophos_5",
        "name_loc": "+{s:value}% Heartstopper Regen Reduction",
        "desc_loc": "",
        "lore_loc": "",
        "notes_loc": [],
        "shard_loc": "",
        "scepter_loc": "",
        "type": 2,
        "behavior": "2",
        "target_team": 0,
        "target_type": 0,
        "flags": 0,
        "damage": 0,
        "immunity": 0,
        "dispellable": 0,
        "max_level": 4,
        "cast_ranges": [
            0
        ],
        "cast_points": [
            0,
            0,
            0,
            0
        ],
        "channel_times": [
            0,
            0,
            0,
            0
        ],
        "cooldowns": [
            0,
            0,
            0,
            0
        ],
        "durations": [
            0,
            0,
            0,
            0
        ],
        "damages": [
            0,
            0,
            0,
            0
        ],
        "mana_costs": [
            0,
            0,
            0,
            0
        ],
        "gold_costs": [],
        "special_values": [
            {
                "name": "value",
                "values_float": [],
                "values_int": [
                    32
                ],
                "is_percentage": false,
                "heading_loc": ""
            }
        ],
        "is_item": false,
        "ability_has_scepter": false,
        "ability_has_shard": false,
        "ability_is_granted_by_scepter": false,
        "ability_is_granted_by_shard": false,
        "item_cost": 0,
        "item_initial_charges": 0,
        "item_neutral_tier": 4294967295,
        "item_stock_max": 0,
        "item_stock_time": 0,
        "item_quality": 0
    },
    "6703": {
        "id": 6703,
        "name": "special_bonus_unique_necrophos_2",
        "name_loc": "+{s:value}  Heartstopper Aura",
        "desc_loc": "",
        "lore_loc": "",
        "notes_loc": [],
        "shard_loc": "",
        "scepter_loc": "",
        "type": 2,
        "behavior": "2",
        "target_team": 0,
        "target_type": 0,
        "flags": 0,
        "damage": 0,
        "immunity": 0,
        "dispellable": 0,
        "max_level": 4,
        "cast_ranges": [
            0
        ],
        "cast_points": [
            0,
            0,
            0,
            0
        ],
        "channel_times": [
            0,
            0,
            0,
            0
        ],
        "cooldowns": [
            0,
            0,
            0,
            0
        ],
        "durations": [
            0,
            0,
            0,
            0
        ],
        "damages": [
            0,
            0,
            0,
            0
        ],
        "mana_costs": [
            0,
            0,
            0,
            0
        ],
        "gold_costs": [],
        "special_values": [
            {
                "name": "value",
                "values_float": [
                    0.5
                ],
                "values_int": [],
                "is_percentage": false,
                "heading_loc": ""
            }
        ],
        "is_item": false,
        "ability_has_scepter": false,
        "ability_has_shard": false,
        "ability_is_granted_by_scepter": false,
        "ability_is_granted_by_shard": false,
        "item_cost": 0,
        "item_initial_charges": 0,
        "item_neutral_tier": 4294967295,
        "item_stock_max": 0,
        "item_stock_time": 0,
        "item_quality": 0
    },
    "6010": {
        "id": 6010,
        "name": "special_bonus_unique_necrophos",
        "name_loc": "-{s:value}s Death Pulse Cooldown",
        "desc_loc": "",
        "lore_loc": "",
        "notes_loc": [],
        "shard_loc": "",
        "scepter_loc": "",
        "type": 2,
        "behavior": "2",
        "target_team": 0,
        "target_type": 0,
        "flags": 0,
        "damage": 0,
        "immunity": 0,
        "dispellable": 0,
        "max_level": 4,
        "cast_ranges": [
            0
        ],
        "cast_points": [
            0,
            0,
            0,
            0
        ],
        "channel_times": [
            0,
            0,
            0,
            0
        ],
        "cooldowns": [
            0,
            0,
            0,
            0
        ],
        "durations": [
            0,
            0,
            0,
            0
        ],
        "damages": [
            0,
            0,
            0,
            0
        ],
        "mana_costs": [
            0,
            0,
            0,
            0
        ],
        "gold_costs": [],
        "special_values": [
            {
                "name": "value",
                "values_float": [
                    2.5
                ],
                "values_int": [],
                "is_percentage": false,
                "heading_loc": ""
            }
        ],
        "is_item": false,
        "ability_has_scepter": false,
        "ability_has_shard": false,
        "ability_is_granted_by_scepter": false,
        "ability_is_granted_by_shard": false,
        "item_cost": 0,
        "item_initial_charges": 0,
        "item_neutral_tier": 4294967295,
        "item_stock_max": 0,
        "item_stock_time": 0,
        "item_quality": 0
    }
}