[
    {
        "id": "https://www.opendota.com/matches/5485090355",
        "name": "Lil",
        "mmr": "7997"
    },
    {
        "id": "https://www.opendota.com/matches/5484280150",
        "name": "Dubu",
        "mmr": "8178"
    },
    {
        "id": "https://www.opendota.com/matches/5484091210",
        "name": "Costabile",
        "mmr": "8415"
    },
    {
        "id": "https://www.opendota.com/matches/5483705235",
        "name": "Lil",
        "mmr": "8037"
    },
    {
        "id": "https://www.opendota.com/matches/5482306513",
        "name": "Paparazi",
        "mmr": "8395"
    },
    {
        "id": "https://www.opendota.com/matches/5482241797",
        "name": "Chalice",
        "mmr": "8505"
    },
    {
        "id": "https://www.opendota.com/matches/5482195755",
        "name": "Meracle",
        "mmr": "7998"
    },
    {
        "id": "https://www.opendota.com/matches/5482087901",
        "name": "Paparazi",
        "mmr": "8857"
    },
    {
        "id": "https://www.opendota.com/matches/5482027965",
        "name": "TOPSON",
        "mmr": "8365"
    },
    {
        "id": "https://www.opendota.com/matches/5481961882",
        "name": "Lil",
        "mmr": "8121"
    },
    {
        "id": "https://www.opendota.com/matches/5481856653",
        "name": "TOPSON",
        "mmr": "8255"
    },
    {
        "id": "https://www.opendota.com/matches/5481833222",
        "name": "TOPSON",
        "mmr": "7813"
    },
    {
        "id": "https://www.opendota.com/matches/5481292387",
        "name": "Supream",
        "mmr": "8634"
    },
    {
        "id": "https://www.opendota.com/matches/5481170917",
        "name": "Feero",
        "mmr": "7089"
    },
    {
        "id": "https://www.opendota.com/matches/5480905794",
        "name": "Ori",
        "mmr": "8908"
    },
    {
        "id": "https://www.opendota.com/matches/5480857723",
        "name": "Gorgc",
        "mmr": "8370"
    },
    {
        "id": "https://www.opendota.com/matches/5480623432",
        "name": "Daxak (smurf)",
        "mmr": "8684"
    },
    {
        "id": "https://www.opendota.com/matches/5480024764",
        "name": "mason",
        "mmr": "8213"
    },
    {
        "id": "https://www.opendota.com/matches/5479624953",
        "name": "Crit",
        "mmr": "8221"
    },
    {
        "id": "https://www.opendota.com/matches/5479390923",
        "name": "Lil",
        "mmr": "8205"
    },
    {
        "id": "https://www.opendota.com/matches/5479222260",
        "name": "Lil",
        "mmr": "8170"
    },
    {
        "id": "https://www.opendota.com/matches/5479063615",
        "name": "Feero",
        "mmr": "6634"
    },
    {
        "id": "https://www.opendota.com/matches/5479053475",
        "name": "TOPSON",
        "mmr": "7652"
    },
    {
        "id": "https://www.opendota.com/matches/5478573624",
        "name": "mason",
        "mmr": "7301"
    },
    {
        "id": "https://www.opendota.com/matches/5478303742",
        "name": "Lil",
        "mmr": "8393"
    },
    {
        "id": "https://www.opendota.com/matches/5478267797",
        "name": "ILTW",
        "mmr": "7856"
    },
    {
        "id": "https://www.opendota.com/matches/5478232021",
        "name": "ILTW",
        "mmr": "8511"
    },
    {
        "id": "https://www.opendota.com/matches/5478189304",
        "name": "Lil",
        "mmr": "8008"
    },
    {
        "id": "https://www.opendota.com/matches/5477745810",
        "name": "Lil",
        "mmr": "8400"
    },
    {
        "id": "https://www.opendota.com/matches/5477632347",
        "name": "Daxak (smurf)",
        "mmr": "8544"
    },
    {
        "id": "https://www.opendota.com/matches/5477038490",
        "name": "Sneyking",
        "mmr": "8543"
    },
    {
        "id": "https://www.opendota.com/matches/5476787399",
        "name": "mason",
        "mmr": "7425"
    }
]