[
    {
        "id": "https://www.opendota.com/matches/5485857883",
        "name": "Handsken",
        "mmr": "8507"
    },
    {
        "id": "https://www.opendota.com/matches/5485543597",
        "name": "iceiceice",
        "mmr": "7746"
    },
    {
        "id": "https://www.opendota.com/matches/5485501501",
        "name": "hFn",
        "mmr": "8607"
    },
    {
        "id": "https://www.opendota.com/matches/5485404912",
        "name": "hFn",
        "mmr": "7954"
    },
    {
        "id": "https://www.opendota.com/matches/5485394349",
        "name": "Costabile",
        "mmr": "8137"
    },
    {
        "id": "https://www.opendota.com/matches/5485380278",
        "name": "hFn",
        "mmr": "7663"
    },
    {
        "id": "https://www.opendota.com/matches/5485350576",
        "name": "hFn",
        "mmr": "7828"
    },
    {
        "id": "https://www.opendota.com/matches/5485032065",
        "name": "March",
        "mmr": "7256"
    },
    {
        "id": "https://www.opendota.com/matches/5484100384",
        "name": "hFn",
        "mmr": "7422"
    },
    {
        "id": "https://www.opendota.com/matches/5484047831",
        "name": "hFn",
        "mmr": "7400"
    },
    {
        "id": "https://www.opendota.com/matches/5483709515",
        "name": "skiter",
        "mmr": "8708"
    },
    {
        "id": "https://www.opendota.com/matches/5483590772",
        "name": "K1 Hector (smurf)",
        "mmr": "7637"
    },
    {
        "id": "https://www.opendota.com/matches/5483302034",
        "name": "Sylar",
        "mmr": "8305"
    },
    {
        "id": "https://www.opendota.com/matches/5482644623",
        "name": "Matumbaman",
        "mmr": "8237"
    },
    {
        "id": "https://www.opendota.com/matches/5482611226",
        "name": "Matumbaman",
        "mmr": "8474"
    },
    {
        "id": "https://www.opendota.com/matches/5482155253",
        "name": "miCKe (smurf)",
        "mmr": "8099"
    },
    {
        "id": "https://www.opendota.com/matches/5481931566",
        "name": "Burning",
        "mmr": "7900"
    },
    {
        "id": "https://www.opendota.com/matches/5481730174",
        "name": "XCalibur",
        "mmr": "7879"
    },
    {
        "id": "https://www.opendota.com/matches/5480999217",
        "name": "Sylar",
        "mmr": "8435"
    },
    {
        "id": "https://www.opendota.com/matches/5480527645",
        "name": "Crystallize",
        "mmr": "8163"
    },
    {
        "id": "https://www.opendota.com/matches/5480521245",
        "name": "XCalibur",
        "mmr": "8831"
    },
    {
        "id": "https://www.opendota.com/matches/5480463430",
        "name": "XCalibur",
        "mmr": "8452"
    },
    {
        "id": "https://www.opendota.com/matches/5480233207",
        "name": "XCalibur",
        "mmr": "7971"
    },
    {
        "id": "https://www.opendota.com/matches/5479029173",
        "name": "Crystallize",
        "mmr": "8679"
    },
    {
        "id": "https://www.opendota.com/matches/5478638861",
        "name": "Timado",
        "mmr": "8686"
    },
    {
        "id": "https://www.opendota.com/matches/5478344105",
        "name": "ILTW",
        "mmr": "8645"
    },
    {
        "id": "https://www.opendota.com/matches/5477243187",
        "name": "XCalibur",
        "mmr": "7905"
    },
    {
        "id": "https://www.opendota.com/matches/5476220040",
        "name": "Daxak (smurf)",
        "mmr": "8565"
    },
    {
        "id": "https://www.opendota.com/matches/5475780979",
        "name": "Scofield",
        "mmr": "7922"
    }
]